LICENSE
MANIFEST.in
README.md
requirements.txt
setup.py
./bch/cli.py
./bch/gateway.py
./bch/mqtt_client.py
./bch/node.py
./bch/tools.py
bch.egg-info/PKG-INFO
bch.egg-info/SOURCES.txt
bch.egg-info/dependency_links.txt
bch.egg-info/entry_points.txt
bch.egg-info/not-zip-safe
bch.egg-info/requires.txt
bch.egg-info/top_level.txt