Metadata-Version: 2.1
Name: bch
Version: 1.2.1
Summary: HARDWARIO Control Tool
Home-page: https://github.com/hardwario/bch-control-tool
Author: HARDWARIO s.r.o.
Author-email: karel.blavka@hardwario.com
License: MIT
Keywords: HARDWARIO,TOWER,gateway,MQTT
Classifier: Development Status :: 5 - Production/Stable
Classifier: Intended Audience :: Developers
Classifier: License :: OSI Approved
Classifier: Operating System :: MacOS :: MacOS X
Classifier: Operating System :: Microsoft :: Windows
Classifier: Operating System :: POSIX
Classifier: Natural Language :: English
Classifier: Programming Language :: Python
Classifier: Programming Language :: Python :: 2
Classifier: Programming Language :: Python :: 2.6
Classifier: Programming Language :: Python :: 2.7
Classifier: Programming Language :: Python :: 3
Classifier: Topic :: Communications
Classifier: Topic :: Internet
Classifier: Topic :: Utilities
Classifier: Environment :: Console
License-File: LICENSE
